Metadata-Version: 2.1
Name: cl-file
Version: 0.3
Summary: Класс для работы с файлами
Author-email: maleksa1296@gmail.com
